easyDL/__init__.py
easyDL/activations/_Activation.py
easyDL/activations/__init__.py
easyDL/activations/identity.py
easyDL/activations/leaky_relu.py
easyDL/activations/relu.py
easyDL/activations/sigmoid.py
easyDL/activations/softmax.py
easyDL/activations/step.py
easyDL/activations/tanh.py
easyDL/evaluation/__init__.py
easyDL/evaluation/evaluation_matrix.py
easyDL/evaluation/plot_conf_mat.py
easyDL/layers/__init__.py
easyDL/layers/batch_norm.py
easyDL/layers/conv_2d.py
easyDL/layers/dense.py
easyDL/layers/dropout.py
easyDL/layers/flatten.py
easyDL/layers/input.py
easyDL/layers/max_pooling_2d.py
easyDL/losses/__init__.py
easyDL/losses/binary_cross_entropy.py
easyDL/losses/categorical_cross_entropy.py
easyDL/losses/mean_squared_error.py
easyDL/losses/sparse_categorical_cross_entropy.py
easyDL/models/__init__.py
easyDL/models/load_model.py
easyDL/models/model.py
easyDL/optimizers/_Optimizer.py
easyDL/optimizers/__init__.py
easyDL/optimizers/ada_grad.py
easyDL/optimizers/adam.py
easyDL/optimizers/gradient_descent.py
easyDL/optimizers/momentum_gd.py
easyDL/optimizers/nesterov_gd.py
easyDL/optimizers/rmsprop.py
easyDL/preprocessing/__init__.py
easyDL/preprocessing/csv/__init__.py
easyDL/preprocessing/csv/load_csv.py
easyDL/preprocessing/datasets/__init__.py
easyDL/preprocessing/datasets/__datasets__/__init__.py
easyDL/preprocessing/datasets/cifar10/__init__.py
easyDL/preprocessing/datasets/cifar10/load_cifar10.py
easyDL/preprocessing/datasets/cifar100/__init__.py
easyDL/preprocessing/datasets/cifar100/load_cifar100.py
easyDL/preprocessing/datasets/mnist/__init__.py
easyDL/preprocessing/datasets/mnist/load_mnist.py
easyDL/preprocessing/image/__init__.py
easyDL/preprocessing/image/load_images.py
easyDL/preprocessing/utils/__init__.py
easyDL/preprocessing/utils/normalize.py
easyDL/preprocessing/utils/shuffle.py
easyDL/visualization/__init__.py
easyDL/visualization/plots.py
py_easyDL-0.0.9.dist-info/LICENSE.txt
py_easyDL-0.0.9.dist-info/METADATA
py_easyDL-0.0.9.dist-info/WHEEL
py_easyDL-0.0.9.dist-info/top_level.txt
py_easyDL-0.0.9.dist-info/RECORD
