Metadata-Version: 2.1
Name: py-easyDL
Version: 0.0.9
Summary: easyDL - Where Deep learning is meant to be easy.
Home-page: https://github.com/ThisisAEmam/easyDL
Author: easyDL team
Author-email: abdoemamofficial@gmail.com
License: UNKNOWN
Platform: UNKNOWN
Classifier: Programming Language :: Python :: 3
Classifier: Programming Language :: Python :: 3.6
Classifier: Programming Language :: Python :: 3.7
Classifier: Programming Language :: Python :: 3.8
Classifier: Programming Language :: Python :: 3.9
Classifier: License :: OSI Approved :: GNU General Public License v2 or later (GPLv2+)
Classifier: Operating System :: OS Independent
Requires-Python: >=3.6
Requires-Dist: numpy
Requires-Dist: pandas
Requires-Dist: matplotlib
Requires-Dist: seaborn
Requires-Dist: opencv-python
Requires-Dist: idx2numpy
Requires-Dist: tqdm
